monitor_gitlab_jobs/__init__.py
monitor_gitlab_jobs/cli.py
monitor_gitlab_jobs-0.2.0.dist-info/METADATA
monitor_gitlab_jobs-0.2.0.dist-info/WHEEL
monitor_gitlab_jobs-0.2.0.dist-info/entry_points.txt
monitor_gitlab_jobs-0.2.0.dist-info/licenses/LICENSE.md
monitor_gitlab_jobs-0.2.0.dist-info/RECORD
