Metadata-Version: 2.4
Name: monitor-gitlab-jobs
Version: 0.2.0
Summary: monitor Gitlab job statuses on the CLI
Project-URL: Homepage, https://github.com/davekch/monitor-gitlab-jobs
Maintainer-email: David Koch <code@davekoch.de>
License-File: LICENSE.md
Requires-Python: >=3.10
Requires-Dist: python-gitlab>=6.0.0
Requires-Dist: rich>=14.0.0
